jupyterlab_hide_code/__init__.py
jupyterlab_hide_code_on_start-1.0.dist-info/LICENSE
jupyterlab_hide_code_on_start-1.0.dist-info/METADATA
jupyterlab_hide_code_on_start-1.0.dist-info/WHEEL
jupyterlab_hide_code_on_start-1.0.dist-info/top_level.txt
jupyterlab_hide_code_on_start-1.0.dist-info/RECORD
