Metadata-Version: 2.1
Name: jupyterlab-hide-code-on-start
Version: 1.0
Summary: A JupyterLab extension
Home-page: UNKNOWN
License: UNKNOWN
Platform: UNKNOWN
License-File: LICENSE
